{
  "requests": {
    "2021-07-28": [
      {
        "id": 1,
        "nim_nik_unit": "4311811039",
        "ruangan": "Lab 705",
        "namaPengaju": "Cristin Yohana",
        "noHpPengaju": "085936702490",
        "jamMulai": "09.00",
        "jamSelesai": "10.00",
        "namaKegiatan": "Mengerjakan Tugas Besar",
        "penanggungJawab": "Bu Maidel Fani",
        "pendampingAcara": "Pak Fandy Neta",
        "pengarahKegiatan": "Bu Maidel Fani",
        "sifat": "Acara Politeknik",
        "jenis": "Diskusi",
        "keterangan": ""
      }
    ],
    "2021-07-29": [
      {
        "id": 2,
        "nim_nik_unit": "4311811039",
        "ruangan": "Lab 805",
        "namaPengaju": "Julio Uliandro",
        "noHpPengaju": "085936702490",
        "jamMulai": "09.00",
        "jamSelesai": "10.00",
        "namaKegiatan": "Rapat besar Himpunan",
        "penanggungJawab": "Bu Maidel Fani",
        "pendampingAcara": "Pak Uuf",
        "pengarahKegiatan": "Bu Sally",
        "sifat": "Acara Mahasiswa/Umum",
        "jenis": "Diskusi",
        "keterangan": ""
      },
      {
        "id": 3,
        "nim_nik_unit": "4311811049",
        "ruangan": "Lab Broadcasting",
        "namaPengaju": "Lutfi Khoerul",
        "noHpPengaju": "085936702490",
        "jamMulai": "11.00",
        "jamSelesai": "17.00",
        "namaKegiatan": "Mengerjakan Tugas Besar",
        "penanggungJawab": "Pak Supardianto",
        "pendampingAcara": "Pak Supardianto",
        "pengarahKegiatan": "Pak Supardianto",
        "sifat": "Acara Politeknik",
        "jenis": "Lain-Lain",
        "keterangan": "Menggunakan peralatan kampus"
      }
    ]
  },
  "borang": [
    {
      "nim_nik_unit": "4311811039",
      "request": [
        {
          "id": "0001",
          "status": "rejected"
        },
        {
          "id": "0004",
          "status": "succeed"
        },
        {
          "id": "0009",
          "status": "procceed"
        },
        {
          "id": "0043",
          "status": "procceed"
        }
      ]
    },
    {
      "nim_nik_unit": "4311811032",
      "request": [
        {
          "id": "0003",
          "status": "succeed"
        },
        {
          "id": "0008",
          "status": "procceed"
        }
      ]
    }
  ],
  "loans": [
    {
      "diterima": true,
      "ruangan": ["Lab 805"],
      "id": "60ffb9cff8eaf50015c567a7",

      "_id": "60ffb9cff8eaf50015c567a7",
      "userId": "4311811039",
      "namaKegiatan": "Membuat Proyek Internal",
      "tanggalMulaiKegiatan": "2021-07-28T07:00:00.000Z",
      "tanggalAkhirKegiatan": "2021-07-28T09:00:00.000Z",
      "penanggungJawab": "Bu Maidel Fani",
      "pengarahKegiatan": "Bu Maidel Fani",
      "jumlahTamu": 20,
      "pendampingAcara": "Bu Maidel Fani",
      "sifat": "Acara Politeknik",
      "jenis": "Diskusi",
      "keterangan": "Tidak ada",
      "namaPengajuRuangan": "Julio Uliandro Sitompul",
      "hpPengajuRuangan": "089685588451",
      "status": "succeed",
      "__v": 0
    },
    {
      "diterima": false,
      "ruangan": ["Lab 601"],
      "id": "60ffba24f8eaf50015c567aa",
      "_id": "60ffba24f8eaf50015c567aa",
      "userId": "4311811049",
      "namaKegiatan": "Membuat Tugas Kuliah Jaringan",
      "tanggalMulaiKegiatan": "2021-07-29T10:00:00.000Z",
      "tanggalAkhirKegiatan": "2021-07-29T12:00:00.000Z",
      "penanggungJawab": "Bu Yeni Rokhayati",
      "pengarahKegiatan": "Bu Yeni Rokhayati",
      "pendampingAcara": "Bu Yeni Rokhayati",
      "jumlahTamu": 30,
      "sifat": "Acara Politeknik",
      "jenis": "Diskusi",
      "keterangan": "Tidak ada",
      "namaPengajuRuangan": "Cristin Yohana Sihombing",
      "hpPengajuRuangan": "0895364673972",
      "status": "procceed",
      "__v": 0
    }
  ]
}
